{
  "local_body_id": "G030506",
  "local_body_name_en": "Chittar",
  "local_body_name_ml": "ചിറ്റാര്‍",
  "local_body_type_en": "Grama Panchayat",
  "local_body_type_ml": "ഗ്രാമ പഞ്ചായത്ത്",
  "category": "Good",
  "assembly": {
    "assembly_id": "114",
    "assembly_name_en": "Konni",
    "assembly_name_ml": "കോന്നി",
    "category": "Normal"
  },
  "district": {
    "district_id": "3",
    "district_name_en": "Pathanamthitta",
    "district_name_ml": "പത്തനംതിട്ട",
    "category": "Normal"
  },
  "wards": [
    {
      "ward_id": "1870f763-3d7b-4f8f-ba3a-2f712409f01c",
      "ward_no": "1",
      "ward_name_en": "Pampini",
      "ward_name_ml": "പാമ്പിനി"
    },
    {
      "ward_id": "0f2d9e8f-0ee7-4ce6-bfe6-1b7fd1173244",
      "ward_no": "2",
      "ward_name_en": "Panniyar",
      "ward_name_ml": "പന്നിയാര്‍"
    },
    {
      "ward_id": "bc2c92b2-e214-4775-9010-69bee3e24e19",
      "ward_no": "3",
      "ward_name_en": "Manakkayam",
      "ward_name_ml": "മണക്കയം"
    },
    {
      "ward_id": "5019bf18-da05-47c7-a246-3ce93480f475",
      "ward_no": "4",
      "ward_name_en": "Chittar",
      "ward_name_ml": "ചിറ്റാര്‍"
    },
    {
      "ward_id": "aa674b4a-d6b2-415a-a93d-7b3654f6c496",
      "ward_no": "5",
      "ward_name_en": "Chittar Thottam",
      "ward_name_ml": "ചിറ്റാര്‍ തോട്ടം"
    },
    {
      "ward_id": "33a65cf4-dfd3-4635-9e1e-e6e1d2f88f91",
      "ward_no": "6",
      "ward_name_en": "Meenkuzhy",
      "ward_name_ml": "മീന്‍കുഴി"
    },
    {
      "ward_id": "ad293fbb-09a7-42bf-b289-aae8a4b1553e",
      "ward_no": "7",
      "ward_name_en": "Kulangaravalley",
      "ward_name_ml": "കുളങ്ങരവാലി"
    },
    {
      "ward_id": "3c125f02-bcc4-4821-96ef-d20600295701",
      "ward_no": "8",
      "ward_name_en": "Vayyattupuzha",
      "ward_name_ml": "വയ്യാറ്റുപുഴ"
    },
    {
      "ward_id": "fb654f83-ffa0-48ea-9a43-5741f2b5900f",
      "ward_no": "9",
      "ward_name_en": "Manpilavu",
      "ward_name_ml": "മണ്‍പിലാവ്"
    },
    {
      "ward_id": "4682fcc0-5a38-47c9-b3fb-2f4444708e64",
      "ward_no": "10",
      "ward_name_en": "Neelipilavu",
      "ward_name_ml": "നീലിപിലാവ്"
    },
    {
      "ward_id": "59db2e29-23c5-410d-a580-26214459a606",
      "ward_no": "11",
      "ward_name_en": "Kattachira",
      "ward_name_ml": "കട്ടച്ചിറ"
    },
    {
      "ward_id": "c5603baa-daa4-41cf-acce-d754026a5a3c",
      "ward_no": "12",
      "ward_name_en": "Chittar Thekkekkara",
      "ward_name_ml": "ചിറ്റാര്‍ തെക്കേക്കര"
    },
    {
      "ward_id": "c1ec3ef5-154b-49f4-a0de-92ff8a40fcc6",
      "ward_no": "13",
      "ward_name_en": "Kodumudi",
      "ward_name_ml": "കൊടുമുടി"
    }
  ],
  "towns": [],
  "issues": {
    "town": [],
    "bus_stop": [],
    "water_body": []
  },
  "geojson_links": {
    "outline": "geojson/local-bodies/outlines/G030506.geojson"
  }
}