{
  "id": "G050504",
  "name_en": "Kadanad",
  "name_ml": "കടനാട്",
  "assembly_id": "93",
  "local_body_type_id": "GP",
  "local_body_type": {
    "id": "GP",
    "name_en": "Grama Panchayat",
    "name_ml": "ഗ്രാമ പഞ്ചായത്ത്"
  },
  "local_body_category": {
    "category": "Perfect"
  },
  "assembly": {
    "id": "93",
    "name_en": "Pala",
    "name_ml": "പാലാ",
    "assembly_category": {
      "category": "Normal"
    }
  },
  "district": {
    "id": "5",
    "name_en": "Kottayam",
    "name_ml": "കോട്ടയം",
    "district_category": {
      "category": "Normal"
    }
  },
  "wards": [
    {
      "id": "6a849282-4771-4faa-99d9-010c0ca826a0",
      "ward_no": "1",
      "name_en": "Manathoor",
      "name_ml": "മാനത്തൂര്‍",
      "ward_collection": {
        "collection_id": 8106,
        "ward_id": "6a849282-4771-4faa-99d9-010c0ca826a0",
        "year_month": "2025-09-01",
        "rate": 75
      }
    },
    {
      "id": "c40caef7-f565-4d36-986b-ede80ce71fbe",
      "ward_no": "2",
      "name_en": "Mattathippara",
      "name_ml": "മറ്റത്തിപ്പാറ",
      "ward_collection": {
        "collection_id": 15086,
        "ward_id": "c40caef7-f565-4d36-986b-ede80ce71fbe",
        "year_month": "2025-09-01",
        "rate": 75
      }
    },
    {
      "id": "313d52df-d142-4d50-af76-7ac43680a57a",
      "ward_no": "3",
      "name_en": "Neeloor",
      "name_ml": "നീലൂര്‍",
      "ward_collection": {
        "collection_id": 3879,
        "ward_id": "313d52df-d142-4d50-af76-7ac43680a57a",
        "year_month": "2025-09-01",
        "rate": 75
      }
    },
    {
      "id": "17f64ad5-ddf4-4db0-9864-9525669b87de",
      "ward_no": "4",
      "name_en": "Kandathimav",
      "name_ml": "കണ്ടത്തിമാവ്",
      "ward_collection": {
        "collection_id": 1981,
        "ward_id": "17f64ad5-ddf4-4db0-9864-9525669b87de",
        "year_month": "2025-09-01",
        "rate": 75
      }
    },
    {
      "id": "1d72566e-4370-4b0b-be34-ef4e275a5ec0",
      "ward_no": "5",
      "name_en": "Maryland",
      "name_ml": "മേരിലാന്‍റ്",
      "ward_collection": {
        "collection_id": 2407,
        "ward_id": "1d72566e-4370-4b0b-be34-ef4e275a5ec0",
        "year_month": "2025-09-01",
        "rate": 65
      }
    },
    {
      "id": "8161526a-f238-4af6-8b8d-4c2d17b312f7",
      "ward_no": "6",
      "name_en": "Kurumannu",
      "name_ml": "കുറുമണ്ണ്",
      "ward_collection": {
        "collection_id": 9917,
        "ward_id": "8161526a-f238-4af6-8b8d-4c2d17b312f7",
        "year_month": "2025-09-01",
        "rate": 95
      }
    },
    {
      "id": "752db253-5cc6-418b-86ec-09504d3a1c1c",
      "ward_no": "7",
      "name_en": "Elivali",
      "name_ml": "എലിവാലി",
      "ward_collection": {
        "collection_id": 8990,
        "ward_id": "752db253-5cc6-418b-86ec-09504d3a1c1c",
        "year_month": "2025-09-01",
        "rate": 95
      }
    },
    {
      "id": "2c5a3958-0261-4a5a-8d4b-a889aa85264d",
      "ward_no": "8",
      "name_en": "Kodumpidy",
      "name_ml": "കൊടുംമ്പിടി",
      "ward_collection": {
        "collection_id": 3496,
        "ward_id": "2c5a3958-0261-4a5a-8d4b-a889aa85264d",
        "year_month": "2025-09-01",
        "rate": 95
      }
    },
    {
      "id": "277f4184-6116-4d6f-94fe-f174968d8466",
      "ward_no": "9",
      "name_en": "Kollappally",
      "name_ml": "കൊല്ലപ്പള്ളി",
      "ward_collection": {
        "collection_id": 3130,
        "ward_id": "277f4184-6116-4d6f-94fe-f174968d8466",
        "year_month": "2025-09-01",
        "rate": 95
      }
    },
    {
      "id": "fc01656d-1222-48a7-a197-e4460d06d270",
      "ward_no": "10",
      "name_en": "Aimcombu",
      "name_ml": "ഐങ്കൊമ്പ്",
      "ward_collection": {
        "collection_id": 19341,
        "ward_id": "fc01656d-1222-48a7-a197-e4460d06d270",
        "year_month": "2025-09-01",
        "rate": 65
      }
    },
    {
      "id": "246c5f37-eb91-4900-8d9c-73a3267792ff",
      "ward_no": "11",
      "name_en": "Kadanad",
      "name_ml": "കടനാട്",
      "ward_collection": {
        "collection_id": 2891,
        "ward_id": "246c5f37-eb91-4900-8d9c-73a3267792ff",
        "year_month": "2025-09-01",
        "rate": 75
      }
    },
    {
      "id": "361fe673-1056-45aa-a2ee-3b3d8fa201ea",
      "ward_no": "12",
      "name_en": "Kavumkandam",
      "name_ml": "കാവുംകണ്ടം",
      "ward_collection": {
        "collection_id": 4264,
        "ward_id": "361fe673-1056-45aa-a2ee-3b3d8fa201ea",
        "year_month": "2025-09-01",
        "rate": 65
      }
    },
    {
      "id": "d2db22ca-cdc5-44fd-a879-4f8477d43731",
      "ward_no": "13",
      "name_en": "Valyathu",
      "name_ml": "വല്യാത്ത്",
      "ward_collection": {
        "collection_id": 16182,
        "ward_id": "d2db22ca-cdc5-44fd-a879-4f8477d43731",
        "year_month": "2025-09-01",
        "rate": 75
      }
    },
    {
      "id": "7a52303f-0338-4842-a57c-f83f4fb7486c",
      "ward_no": "14",
      "name_en": "Pizhaku",
      "name_ml": "പിഴക്",
      "ward_collection": {
        "collection_id": 9387,
        "ward_id": "7a52303f-0338-4842-a57c-f83f4fb7486c",
        "year_month": "2025-09-01",
        "rate": 75
      }
    }
  ],
  "towns": [],
  "issues": {
    "town": {},
    "bus_stop": [],
    "water_body": []
  },
  "geojson_links": {
    "outline": "geojson/local-bodies/outlines/kadanad.geojson"
  }
}