{
  "id": "G071304",
  "name_en": "Parakkadavu",
  "name_ml": "പാറക്കടവ്",
  "assembly_id": "75",
  "local_body_type": {
    "id": "CORP",
    "name_en": "Corporation",
    "name_ml": "കോർപ്പറേഷൻ"
  },
  "local_body_category": {
    "category": "Normal"
  },
  "assembly": {
    "id": "75",
    "name_en": "Angamaly",
    "name_ml": "അങ്കമാലി",
    "assembly_category": {
      "category": "Normal"
    }
  },
  "district": {
    "id": "7",
    "name_en": "Ernakulam",
    "name_ml": "എറണാകുളം",
    "district_category": {
      "category": "Normal"
    }
  },
  "wards": [
    {
      "id": "764cfe32-8a34-4cb3-947e-c622e5d5b92a",
      "ward_no": "1",
      "name_en": "Mambra West",
      "name_ml": "മാമ്പ്ര പടിഞ്ഞാറ്",
      "ward_collection": {
        "collection_id": 9075,
        "ward_id": "764cfe32-8a34-4cb3-947e-c622e5d5b92a",
        "year_month": "2025-09-01",
        "rate": 75
      }
    },
    {
      "id": "e1d3ffe1-472f-4f76-b310-4ddbc158d35c",
      "ward_no": "2",
      "name_en": "Mambra East",
      "name_ml": "മാമ്പ്ര കിഴക്ക്",
      "ward_collection": {
        "collection_id": 17300,
        "ward_id": "e1d3ffe1-472f-4f76-b310-4ddbc158d35c",
        "year_month": "2025-09-01",
        "rate": 75
      }
    },
    {
      "id": "bb7c2c9b-c2de-470f-a9d7-75d8d2ca2678",
      "ward_no": "3",
      "name_en": "Puliyanam East",
      "name_ml": "പുളിയനം കിഴക്ക്",
      "ward_collection": {
        "collection_id": 14437,
        "ward_id": "bb7c2c9b-c2de-470f-a9d7-75d8d2ca2678",
        "year_month": "2025-09-01",
        "rate": 75
      }
    },
    {
      "id": "ba79990c-d7aa-41ff-b13c-4070f3af89e0",
      "ward_no": "4",
      "name_en": "Puliyanam South",
      "name_ml": "പുളിയനം തെക്ക്",
      "ward_collection": {
        "collection_id": 14358,
        "ward_id": "ba79990c-d7aa-41ff-b13c-4070f3af89e0",
        "year_month": "2025-09-01",
        "rate": 65
      }
    },
    {
      "id": "3d6beb84-f624-4e43-bac3-3e08a73b8f0b",
      "ward_no": "5",
      "name_en": "Kodussery",
      "name_ml": "കോടുശ്ശേരി",
      "ward_collection": {
        "collection_id": 4796,
        "ward_id": "3d6beb84-f624-4e43-bac3-3e08a73b8f0b",
        "year_month": "2025-09-01",
        "rate": 95
      }
    },
    {
      "id": "566ee04a-b751-4bb4-bcff-b862b25ed1a5",
      "ward_no": "6",
      "name_en": "Vattaparambu",
      "name_ml": "വട്ടപ്പറമ്പ്",
      "ward_collection": {
        "collection_id": 6668,
        "ward_id": "566ee04a-b751-4bb4-bcff-b862b25ed1a5",
        "year_month": "2025-09-01",
        "rate": 65
      }
    },
    {
      "id": "4c457bb9-8086-4568-a336-147fda80eda7",
      "ward_no": "7",
      "name_en": "Kurumassery East",
      "name_ml": "കുറുമശ്ശേരി കിഴക്ക്",
      "ward_collection": {
        "collection_id": 5903,
        "ward_id": "4c457bb9-8086-4568-a336-147fda80eda7",
        "year_month": "2025-09-01",
        "rate": 75
      }
    },
    {
      "id": "30d8fa8c-3af4-4149-93f1-fcd93f74acb7",
      "ward_no": "8",
      "name_en": "Kurumassery West",
      "name_ml": "കുറുമശ്ശേരി പടിഞ്ഞാറ്",
      "ward_collection": {
        "collection_id": 3840,
        "ward_id": "30d8fa8c-3af4-4149-93f1-fcd93f74acb7",
        "year_month": "2025-09-01",
        "rate": 65
      }
    },
    {
      "id": "b5b573ed-783d-49a3-a2d7-113dc25da972",
      "ward_no": "9",
      "name_en": "Kurumassery North",
      "name_ml": "കുറുമശ്ശേരി വടക്ക്",
      "ward_collection": {
        "collection_id": 13998,
        "ward_id": "b5b573ed-783d-49a3-a2d7-113dc25da972",
        "year_month": "2025-09-01",
        "rate": 75
      }
    },
    {
      "id": "ddab81af-02a2-4aaa-b489-3ab908d013d6",
      "ward_no": "10",
      "name_en": "Moozhikkulam",
      "name_ml": "മൂഴിക്കുളം",
      "ward_collection": {
        "collection_id": 16985,
        "ward_id": "ddab81af-02a2-4aaa-b489-3ab908d013d6",
        "year_month": "2025-09-01",
        "rate": 65
      }
    },
    {
      "id": "a459e383-2d09-4acd-850d-53c69e08afc0",
      "ward_no": "11",
      "name_en": "Parakkadavu South",
      "name_ml": "പാറക്കടവ് തെക്ക്",
      "ward_collection": {
        "collection_id": 12594,
        "ward_id": "a459e383-2d09-4acd-850d-53c69e08afc0",
        "year_month": "2025-09-01",
        "rate": 75
      }
    },
    {
      "id": "958956e3-6b64-4428-9301-db65acbecb81",
      "ward_no": "12",
      "name_en": "Parakkadavu North",
      "name_ml": "പാറക്കടവ് വടക്ക്",
      "ward_collection": {
        "collection_id": 11474,
        "ward_id": "958956e3-6b64-4428-9301-db65acbecb81",
        "year_month": "2025-09-01",
        "rate": 75
      }
    },
    {
      "id": "739f095c-6b7c-432b-8bb7-373a62f6106d",
      "ward_no": "13",
      "name_en": "Poovathussery",
      "name_ml": "പൂവത്തുശ്ശേരി",
      "ward_collection": {
        "collection_id": 8874,
        "ward_id": "739f095c-6b7c-432b-8bb7-373a62f6106d",
        "year_month": "2025-09-01",
        "rate": 95
      }
    },
    {
      "id": "0e129102-380f-406e-bb2e-96dbae0d0d73",
      "ward_no": "14",
      "name_en": "Kunnappyllissery",
      "name_ml": "കുന്നപ്പിള്ളിശ്ശേരി",
      "ward_collection": {
        "collection_id": 1232,
        "ward_id": "0e129102-380f-406e-bb2e-96dbae0d0d73",
        "year_month": "2025-09-01",
        "rate": 65
      }
    },
    {
      "id": "6cb82af5-04b5-4bb0-bbc2-678dce6c13a4",
      "ward_no": "15",
      "name_en": "Elavoor",
      "name_ml": "എളവൂര്‍",
      "ward_collection": {
        "collection_id": 8296,
        "ward_id": "6cb82af5-04b5-4bb0-bbc2-678dce6c13a4",
        "year_month": "2025-09-01",
        "rate": 65
      }
    },
    {
      "id": "54128ca5-fdab-48d4-9984-01410d32481b",
      "ward_no": "16",
      "name_en": "Puliyanam",
      "name_ml": "പുളിയനം",
      "ward_collection": {
        "collection_id": 6501,
        "ward_id": "54128ca5-fdab-48d4-9984-01410d32481b",
        "year_month": "2025-09-01",
        "rate": 75
      }
    },
    {
      "id": "34215a0d-15a1-41d9-b816-c571c4d4e7ba",
      "ward_no": "17",
      "name_en": "Elavoor North",
      "name_ml": "എളവൂര്‍ വടക്ക്",
      "ward_collection": {
        "collection_id": 4112,
        "ward_id": "34215a0d-15a1-41d9-b816-c571c4d4e7ba",
        "year_month": "2025-09-01",
        "rate": 75
      }
    },
    {
      "id": "b3437f75-1af0-402c-a3c7-c884f993c63c",
      "ward_no": "18",
      "name_en": "Puliyanam West",
      "name_ml": "പുളിയനം പടിഞ്ഞാറ്",
      "ward_collection": {
        "collection_id": 13795,
        "ward_id": "b3437f75-1af0-402c-a3c7-c884f993c63c",
        "year_month": "2025-09-01",
        "rate": 65
      }
    }
  ],
  "towns": [],
  "issues": {
    "town": {},
    "bus_stop": [],
    "water_body": []
  },
  "geojson_links": {
    "outline": "geojson/local-bodies/outlines/parakkadavu.geojson"
  }
}