{
  "id": "G081501",
  "name_en": "Aloor",
  "name_ml": "ആളൂര്‍",
  "assembly_id": "70",
  "local_body_type": {
    "id": "CORP",
    "name_en": "Corporation",
    "name_ml": "കോർപ്പറേഷൻ"
  },
  "local_body_category": {
    "category": "Good"
  },
  "assembly": {
    "id": "70",
    "name_en": "Irinjalakuda",
    "name_ml": "ഇരിങ്ങാലക്കുട",
    "assembly_category": {
      "category": "Normal"
    }
  },
  "district": {
    "id": "8",
    "name_en": "Thrissur",
    "name_ml": "തൃശ്ശൂർ",
    "district_category": {
      "category": "Normal"
    }
  },
  "wards": [
    {
      "id": "e21a344c-51e4-4ecd-b679-5b877434d699",
      "ward_no": "1",
      "name_en": "Panjappilly",
      "name_ml": "പഞ്ഞപ്പിള്ളി",
      "ward_collection": {
        "collection_id": 17320,
        "ward_id": "e21a344c-51e4-4ecd-b679-5b877434d699",
        "year_month": "2025-09-01",
        "rate": 75
      }
    },
    {
      "id": "8d2250aa-0fc1-4658-99dc-afc59b95af97",
      "ward_no": "2",
      "name_en": "Vadakkummury",
      "name_ml": "വടക്കുംമുറി",
      "ward_collection": {
        "collection_id": 10828,
        "ward_id": "8d2250aa-0fc1-4658-99dc-afc59b95af97",
        "year_month": "2025-09-01",
        "rate": 65
      }
    },
    {
      "id": "019a89dd-1242-4998-aa19-42dc366045d8",
      "ward_no": "3",
      "name_en": "Kallettumkara North",
      "name_ml": "കല്ലേറ്റുംകര നോർത്ത്",
      "ward_collection": {
        "collection_id": 288,
        "ward_id": "019a89dd-1242-4998-aa19-42dc366045d8",
        "year_month": "2025-09-01",
        "rate": 75
      }
    },
    {
      "id": "4c33adfb-b521-46ca-8ac2-bcff24e73905",
      "ward_no": "4",
      "name_en": "Anathadam",
      "name_ml": "ആനത്തടം",
      "ward_collection": {
        "collection_id": 5897,
        "ward_id": "4c33adfb-b521-46ca-8ac2-bcff24e73905",
        "year_month": "2025-09-01",
        "rate": 95
      }
    },
    {
      "id": "ac07a7f4-50a3-4924-af5c-8db48926627b",
      "ward_no": "5",
      "name_en": "Kadalichira",
      "name_ml": "കദളിച്ചിറ",
      "ward_collection": {
        "collection_id": 13182,
        "ward_id": "ac07a7f4-50a3-4924-af5c-8db48926627b",
        "year_month": "2025-09-01",
        "rate": 75
      }
    },
    {
      "id": "de5bda2d-956e-4218-b599-e34735024d38",
      "ward_no": "6",
      "name_en": "Thanippara",
      "name_ml": "താണിപ്പാറ",
      "ward_collection": {
        "collection_id": 17049,
        "ward_id": "de5bda2d-956e-4218-b599-e34735024d38",
        "year_month": "2025-09-01",
        "rate": 75
      }
    },
    {
      "id": "d14773a2-73af-4fbd-bddb-2a77fd915cd9",
      "ward_no": "7",
      "name_en": "Urumpankunnu",
      "name_ml": "ഉറുമ്പൻകുന്ന്",
      "ward_collection": {
        "collection_id": 16075,
        "ward_id": "d14773a2-73af-4fbd-bddb-2a77fd915cd9",
        "year_month": "2025-09-01",
        "rate": 65
      }
    },
    {
      "id": "7b688166-3a01-4fd1-ad38-b288c2705dfb",
      "ward_no": "8",
      "name_en": "Vellanchira",
      "name_ml": "വെള്ളാഞ്ചിറ",
      "ward_collection": {
        "collection_id": 9474,
        "ward_id": "7b688166-3a01-4fd1-ad38-b288c2705dfb",
        "year_month": "2025-09-01",
        "rate": 75
      }
    },
    {
      "id": "6f5e59e5-393c-46f4-a66e-68f762c76607",
      "ward_no": "9",
      "name_en": "East Thiruthiparampu",
      "name_ml": "ഈസ്റ്റ്‌ തിരുത്തിപറമ്പ്",
      "ward_collection": {
        "collection_id": 8516,
        "ward_id": "6f5e59e5-393c-46f4-a66e-68f762c76607",
        "year_month": "2025-09-01",
        "rate": 75
      }
    },
    {
      "id": "6dd880d9-b6f2-413e-884d-da2fd3762cc7",
      "ward_no": "10",
      "name_en": "West Thiruthiparambu",
      "name_ml": "വെസ്റ്റ്  തിരുത്തിപറമ്പ്",
      "ward_collection": {
        "collection_id": 8383,
        "ward_id": "6dd880d9-b6f2-413e-884d-da2fd3762cc7",
        "year_month": "2025-09-01",
        "rate": 75
      }
    },
    {
      "id": "7326f26e-d320-43c2-a68a-57f630f36bb6",
      "ward_no": "11",
      "name_en": "Karoor",
      "name_ml": "കാരൂർ",
      "ward_collection": {
        "collection_id": 8831,
        "ward_id": "7326f26e-d320-43c2-a68a-57f630f36bb6",
        "year_month": "2025-09-01",
        "rate": 75
      }
    },
    {
      "id": "e4de609b-592e-49f1-96be-2cf782184898",
      "ward_no": "12",
      "name_en": "Kuzhikattussery",
      "name_ml": "കുഴിക്കാട്ടുശ്ശേരി",
      "ward_collection": {
        "collection_id": 17539,
        "ward_id": "e4de609b-592e-49f1-96be-2cf782184898",
        "year_month": "2025-09-01",
        "rate": 95
      }
    },
    {
      "id": "bd3cefd1-dd81-477c-aced-dc7f706a3409",
      "ward_no": "13",
      "name_en": "Kombodinjamakal",
      "name_ml": "കൊമ്പൊടിഞ്ഞാമാക്കൽ",
      "ward_collection": {
        "collection_id": 14567,
        "ward_id": "bd3cefd1-dd81-477c-aced-dc7f706a3409",
        "year_month": "2025-09-01",
        "rate": 75
      }
    },
    {
      "id": "b3a4c7ba-f7ff-4d6a-8dc1-af648a1b0a34",
      "ward_no": "14",
      "name_en": "Parambi",
      "name_ml": "പറമ്പി",
      "ward_collection": {
        "collection_id": 13825,
        "ward_id": "b3a4c7ba-f7ff-4d6a-8dc1-af648a1b0a34",
        "year_month": "2025-09-01",
        "rate": 95
      }
    },
    {
      "id": "f59739bc-4d5c-4359-a39a-b08f10bf75aa",
      "ward_no": "15",
      "name_en": "Kannikkara",
      "name_ml": "കണ്ണിക്കര",
      "ward_collection": {
        "collection_id": 18819,
        "ward_id": "f59739bc-4d5c-4359-a39a-b08f10bf75aa",
        "year_month": "2025-09-01",
        "rate": 75
      }
    },
    {
      "id": "44fca96c-1408-45cd-bf17-3dfda114c238",
      "ward_no": "16",
      "name_en": "Thazhekad",
      "name_ml": "താഴേക്കാട്",
      "ward_collection": {
        "collection_id": 5311,
        "ward_id": "44fca96c-1408-45cd-bf17-3dfda114c238",
        "year_month": "2025-09-01",
        "rate": 75
      }
    },
    {
      "id": "5bfb41ae-732f-4d27-b262-1200903da017",
      "ward_no": "17",
      "name_en": "Kallettumkara South",
      "name_ml": "കല്ലേറ്റുംകര സൗത്ത്",
      "ward_collection": {
        "collection_id": 7074,
        "ward_id": "5bfb41ae-732f-4d27-b262-1200903da017",
        "year_month": "2025-09-01",
        "rate": 75
      }
    },
    {
      "id": "d74a736a-02bb-4206-a915-42413843f34f",
      "ward_no": "18",
      "name_en": "Manattukunnu",
      "name_ml": "മാനാട്ടുകുന്ന്",
      "ward_collection": {
        "collection_id": 16492,
        "ward_id": "d74a736a-02bb-4206-a915-42413843f34f",
        "year_month": "2025-09-01",
        "rate": 65
      }
    },
    {
      "id": "aa9f5d89-7962-4c18-94b5-94bc13214c1b",
      "ward_no": "19",
      "name_en": "Aloor",
      "name_ml": "ആളൂർ",
      "ward_collection": {
        "collection_id": 13075,
        "ward_id": "aa9f5d89-7962-4c18-94b5-94bc13214c1b",
        "year_month": "2025-09-01",
        "rate": 75
      }
    },
    {
      "id": "75e13eb2-7798-40ae-b5d3-da96a614bf16",
      "ward_no": "20",
      "name_en": "Porunnakunnu",
      "name_ml": "പൊരുന്നകുന്ന്",
      "ward_collection": {
        "collection_id": 9041,
        "ward_id": "75e13eb2-7798-40ae-b5d3-da96a614bf16",
        "year_month": "2025-09-01",
        "rate": 75
      }
    },
    {
      "id": "593b9c4d-15bc-4351-9403-c708030695d6",
      "ward_no": "21",
      "name_en": "Sholayar",
      "name_ml": "ഷോളയാർ",
      "ward_collection": {
        "collection_id": 6895,
        "ward_id": "593b9c4d-15bc-4351-9403-c708030695d6",
        "year_month": "2025-09-01",
        "rate": 95
      }
    },
    {
      "id": "c626704a-8a36-45f5-8d8f-ba9b5a15be66",
      "ward_no": "22",
      "name_en": "Karakkulam",
      "name_ml": "കാരാക്കുളം",
      "ward_collection": {
        "collection_id": 15213,
        "ward_id": "c626704a-8a36-45f5-8d8f-ba9b5a15be66",
        "year_month": "2025-09-01",
        "rate": 75
      }
    },
    {
      "id": "9d07b028-9341-45a7-8dea-f57470d91a48",
      "ward_no": "23",
      "name_en": "Vallakkunnu",
      "name_ml": "വല്ലക്കുന്ന്",
      "ward_collection": {
        "collection_id": 12026,
        "ward_id": "9d07b028-9341-45a7-8dea-f57470d91a48",
        "year_month": "2025-09-01",
        "rate": 75
      }
    }
  ],
  "towns": [],
  "issues": {
    "town": {},
    "bus_stop": [],
    "water_body": []
  },
  "geojson_links": {
    "outline": "geojson/local-bodies/outlines/aloor.geojson"
  }
}