{
  "id": "G091106",
  "name_en": "Nenmara",
  "name_ml": "നെന്മാറ",
  "assembly_id": "59",
  "local_body_type_id": "GP",
  "local_body_type": {
    "id": "GP",
    "name_en": "Grama Panchayat",
    "name_ml": "ഗ്രാമ പഞ്ചായത്ത്"
  },
  "local_body_category": {
    "category": "Good"
  },
  "assembly": {
    "id": "59",
    "name_en": "Nenmara",
    "name_ml": "നെന്മാറ",
    "assembly_category": {
      "category": "Normal"
    }
  },
  "district": {
    "id": "9",
    "name_en": "Palakkad",
    "name_ml": "പാലക്കാട്",
    "district_category": {
      "category": "Normal"
    }
  },
  "wards": [
    {
      "id": "a977552b-ace9-4ad5-ad2e-10f8bd2e0995",
      "ward_no": "1",
      "name_en": "Ayinampadam",
      "name_ml": "അയിനംപാടം",
      "rate": 65
    },
    {
      "id": "00e6f1ec-5acf-4acc-837d-d955d7bb2779",
      "ward_no": "2",
      "name_en": "Puthanthara",
      "name_ml": "പുത്തന്‍തറ",
      "rate": 75
    },
    {
      "id": "9c405582-7e7c-4314-989a-a3ec27aab1df",
      "ward_no": "3",
      "name_en": "Vallanghy",
      "name_ml": "വല്ലങ്ങി",
      "rate": 75
    },
    {
      "id": "de044e0e-f412-4925-8df2-1faf9e711559",
      "ward_no": "4",
      "name_en": "Pullikalthara",
      "name_ml": "പുളിക്കല്‍തറ",
      "rate": 75
    },
    {
      "id": "35a291ca-e381-449f-900e-eb6dcf67aff7",
      "ward_no": "5",
      "name_en": "Nemmarapadam",
      "name_ml": "നെന്മാറപാടം",
      "rate": 75
    },
    {
      "id": "6c8cf8dd-9df4-46eb-956e-d63844503fe3",
      "ward_no": "6",
      "name_en": "Kossanipallam",
      "name_ml": "കൊശ്ശനിപ്പള്ളം",
      "rate": 95
    },
    {
      "id": "1d83dab6-468f-4bba-b31c-853a0f42228a",
      "ward_no": "7",
      "name_en": "Vithanassery",
      "name_ml": "വിത്തനശ്ശേരി",
      "rate": 75
    },
    {
      "id": "09914ed8-5a47-40b4-be70-0b32c0904878",
      "ward_no": "8",
      "name_en": "Pazhatharakad",
      "name_ml": "പഴതറക്കാട്",
      "rate": 75
    },
    {
      "id": "090c76f5-1ef0-44f3-9070-0686d4d44ae8",
      "ward_no": "9",
      "name_en": "Nellipadam",
      "name_ml": "നെല്ലിപ്പാടം",
      "rate": 75
    },
    {
      "id": "52705f2d-1c91-4840-954e-d3fa8181a521",
      "ward_no": "10",
      "name_en": "Ayyapanpara",
      "name_ml": "അയ്യപ്പന്‍പ്പാറ",
      "rate": 75
    },
    {
      "id": "bfa9d472-662d-4abb-beb9-30f0d067e14e",
      "ward_no": "11",
      "name_en": "Pothundy",
      "name_ml": "പോത്തുണ്ടി",
      "rate": 75
    },
    {
      "id": "9c08f156-ac98-488d-ba5b-e0afd3f50ea1",
      "ward_no": "12",
      "name_en": "Mattayi",
      "name_ml": "മാട്ടായി",
      "rate": 75
    },
    {
      "id": "1b7dc142-3ba0-4bf6-ba3d-97857ee314ff",
      "ward_no": "13",
      "name_en": "Nellikad",
      "name_ml": "നെല്ലിക്കാട്",
      "rate": 75
    },
    {
      "id": "4373088b-fc35-4450-bd56-93e54afad0e7",
      "ward_no": "14",
      "name_en": "Chathamangalam",
      "name_ml": "ചാത്തമംഗലം",
      "rate": 95
    },
    {
      "id": "e48f4c13-527a-450b-934f-bc6fe700bd6c",
      "ward_no": "15",
      "name_en": "Pezhumpara",
      "name_ml": "പേഴുംപാറ",
      "rate": 95
    },
    {
      "id": "c229e605-2ace-4195-8094-b613d5db67d7",
      "ward_no": "16",
      "name_en": "Palaparambu",
      "name_ml": "പാലപ്പറന്പ്",
      "rate": 95
    },
    {
      "id": "bd62cd66-d650-4dbe-9179-b2d08edb87e1",
      "ward_no": "17",
      "name_en": "Nemmara",
      "name_ml": "നെന്മാറ",
      "rate": 95
    },
    {
      "id": "0d72ca94-89a8-49e7-805c-61125fda8ff8",
      "ward_no": "18",
      "name_en": "Vakkavu",
      "name_ml": "വക്കാവ്",
      "rate": 75
    },
    {
      "id": "71845439-aad6-4186-b052-2cfd88099dd3",
      "ward_no": "19",
      "name_en": "Kalmokku",
      "name_ml": "കല്‍മുക്ക്",
      "rate": 75
    },
    {
      "id": "53ee2d9e-8b4c-4272-9343-c95942ca06f0",
      "ward_no": "20",
      "name_en": "Chennamkode",
      "name_ml": "ചെന്ദംങ്കോട്",
      "rate": 95
    }
  ],
  "towns": [],
  "issues": {
    "town": {},
    "bus_stop": [],
    "water_body": []
  },
  "geojson_links": {
    "outline": "geojson/local-bodies/outlines/nenmara.geojson"
  }
}